LICENSE.md
MANIFEST.in
README.md
pyproject.toml
setup.py
cython/frame.pyx
pyteleport/__init__.py
pyteleport/bytecode.py
pyteleport/dill_tools.py
pyteleport/minias.py
pyteleport/morph.py
pyteleport/primitives.py
pyteleport/snapshot.py
pyteleport/teleport.py
pyteleport/test_scripts.py
pyteleport/util.py
pyteleport.egg-info/PKG-INFO
pyteleport.egg-info/SOURCES.txt
pyteleport.egg-info/dependency_links.txt
pyteleport.egg-info/requires.txt
pyteleport.egg-info/top_level.txt
pyteleport/tests/__init__.py
pyteleport/tests/_test_dump.py
pyteleport/tests/_test_dump_nested.py
pyteleport/tests/_test_teleport_async.py
pyteleport/tests/_test_teleport_basic.py
pyteleport/tests/_test_teleport_class.py
pyteleport/tests/_test_teleport_class_static.py
pyteleport/tests/_test_teleport_custom_load.py
pyteleport/tests/_test_teleport_except.py
pyteleport/tests/_test_teleport_except_another.py
pyteleport/tests/_test_teleport_except_nonlocal.py
pyteleport/tests/_test_teleport_finally.py
pyteleport/tests/_test_teleport_generator.py
pyteleport/tests/_test_teleport_generator_count.py
pyteleport/tests/_test_teleport_generator_nested.py
pyteleport/tests/_test_teleport_generator_range.py
pyteleport/tests/_test_teleport_generator_stack.py
pyteleport/tests/_test_teleport_loop.py
pyteleport/tests/_test_teleport_multi.py
pyteleport/tests/_test_teleport_nested.py
pyteleport/tests/_test_teleport_try.py
pyteleport/tests/_test_teleport_try_w_finally.py
pyteleport/tests/_test_teleport_try_w_stack.py
pyteleport/tests/_test_teleport_with.py
pyteleport/tests/helpers.py