Metadata-Version: 2.1
Name: pyteleport
Version: 0.2.1.post2
Summary: A proof-of-concept snapshot, transmission and restoring python runtime
Author: pulkin
Author-email: gpulkin@gmail.com
License: UNKNOWN
Platform: UNKNOWN
License-File: LICENSE.md
